dimensionalos/__init__.py
dimensionalos-0.0.0.dist-info/METADATA
dimensionalos-0.0.0.dist-info/WHEEL
dimensionalos-0.0.0.dist-info/top_level.txt
dimensionalos-0.0.0.dist-info/RECORD
