Metadata-Version: 2.1
Name: dimensionalos
Version: 0.0.0
Summary: Coming soon
Author-email: Stash Pomichter <stash@dimensionalOS.com>
